aish/__init__.py
aish/__main__.py
aish/agent.py
aish/cli.py
aish/config.py
aish/history.py
aish/safety.py
aish/utils.py
aish_local-1.0.0.dist-info/licenses/LICENSE
aish_local-1.0.0.dist-info/METADATA
aish_local-1.0.0.dist-info/WHEEL
aish_local-1.0.0.dist-info/entry_points.txt
aish_local-1.0.0.dist-info/top_level.txt
aish_local-1.0.0.dist-info/RECORD
