Metadata-Version: 2.4
Name: aish-local
Version: 1.0.0
Summary: Talk to your terminal in natural language, get safe Linux commands (Ollama LLMs only, no thinking models).
Author-email: Penumala Nani <pnani18dec@gmail.com>
License-Expression: MIT
Requires-Python: >=3.8
License-File: LICENSE
Requires-Dist: requests
Dynamic: license-file
